Metadata-Version: 2.1
Name: poetry-demo-amanda
Version: 0.1.0
Summary: 
Author: Amanda
Author-email: z4ghjdyx@foxmail.com
Requires-Python: >=3.9,<4.0
Classifier: Programming Language :: Python :: 3
Classifier: Programming Language :: Python :: 3.9
Classifier: Programming Language :: Python :: 3.10
Classifier: Programming Language :: Python :: 3.11
Requires-Dist: pendulum (>=2.1.2,<3.0.0)
